LICENSE
MANIFEST.in
README.rst
setup.cfg
setup.py
Mopidy_AudioAddict.egg-info/PKG-INFO
Mopidy_AudioAddict.egg-info/SOURCES.txt
Mopidy_AudioAddict.egg-info/dependency_links.txt
Mopidy_AudioAddict.egg-info/entry_points.txt
Mopidy_AudioAddict.egg-info/not-zip-safe
Mopidy_AudioAddict.egg-info/requires.txt
Mopidy_AudioAddict.egg-info/top_level.txt
mopidy_audioaddict/__init__.py
mopidy_audioaddict/actor.py
mopidy_audioaddict/client.py
mopidy_audioaddict/ext.conf
mopidy_audioaddict/translator.py
tests/test_actor.py
tests/test_client.py
tests/test_translator.py