Metadata-Version: 1.1
Name: Mopidy-AudioAddict
Version: 0.2.6
Summary: Mopidy extension for the AudioAddict network of radiostations
Home-page: https://github.com/nilicule/mopidy-audioaddict
Author: Remco Brink
Author-email: remco@rc6.org
License: Apache License, Version 2.0
Platform: UNKNOWN
Classifier: Environment :: No Input/Output (Daemon)
Classifier: Intended Audience :: End Users/Desktop
Classifier: License :: OSI Approved :: Apache Software License
Classifier: Operating System :: OS Independent
Classifier: Programming Language :: Python :: 2
Classifier: Topic :: Multimedia :: Sound/Audio :: Players
